{
	"backtraceGraph" : 
	{
		"commands" : 
		[
			"install"
		],
		"files" : 
		[
			"external/mimalloc/CMakeLists.txt"
		],
		"nodes" : 
		[
			{
				"file" : 0
			},
			{
				"command" : 0,
				"file" : 0,
				"line" : 284,
				"parent" : 0
			},
			{
				"command" : 0,
				"file" : 0,
				"line" : 285,
				"parent" : 0
			},
			{
				"command" : 0,
				"file" : 0,
				"line" : 308,
				"parent" : 0
			},
			{
				"command" : 0,
				"file" : 0,
				"line" : 312,
				"parent" : 0
			},
			{
				"command" : 0,
				"file" : 0,
				"line" : 313,
				"parent" : 0
			},
			{
				"command" : 0,
				"file" : 0,
				"line" : 314,
				"parent" : 0
			},
			{
				"command" : 0,
				"file" : 0,
				"line" : 315,
				"parent" : 0
			},
			{
				"command" : 0,
				"file" : 0,
				"line" : 316,
				"parent" : 0
			},
			{
				"command" : 0,
				"file" : 0,
				"line" : 345,
				"parent" : 0
			}
		]
	},
	"installers" : 
	[
		{
			"backtrace" : 1,
			"component" : "Unspecified",
			"destination" : "lib/mimalloc-1.7",
			"paths" : 
			[
				"external/mimalloc/mimalloc-debug.lib"
			],
			"targetId" : "mimalloc::@ee08262cb61d95d910f0",
			"targetIndex" : 11,
			"targetIsImportLibrary" : true,
			"type" : "target"
		},
		{
			"backtrace" : 1,
			"component" : "Unspecified",
			"destination" : "lib/mimalloc-1.7",
			"paths" : 
			[
				"external/mimalloc/mimalloc-debug.dll"
			],
			"targetId" : "mimalloc::@ee08262cb61d95d910f0",
			"targetIndex" : 11,
			"type" : "target"
		},
		{
			"backtrace" : 2,
			"component" : "Unspecified",
			"destination" : "share/mimalloc-1.7/cmake",
			"exportName" : "mimalloc",
			"exportTargets" : 
			[
				{
					"id" : "mimalloc::@ee08262cb61d95d910f0",
					"index" : 11
				},
				{
					"id" : "mimalloc-static::@ee08262cb61d95d910f0",
					"index" : 13
				}
			],
			"paths" : 
			[
				"external/mimalloc/CMakeFiles/Export/share/mimalloc-1.7/cmake/mimalloc.cmake"
			],
			"type" : "export"
		},
		{
			"backtrace" : 3,
			"component" : "Unspecified",
			"destination" : "lib/mimalloc-1.7",
			"paths" : 
			[
				"external/mimalloc/mimalloc-static-debug.lib"
			],
			"targetId" : "mimalloc-static::@ee08262cb61d95d910f0",
			"targetIndex" : 13,
			"type" : "target"
		},
		{
			"backtrace" : 4,
			"component" : "Unspecified",
			"destination" : "include/mimalloc-1.7",
			"paths" : 
			[
				"external/mimalloc/include/mimalloc.h"
			],
			"type" : "file"
		},
		{
			"backtrace" : 5,
			"component" : "Unspecified",
			"destination" : "include/mimalloc-1.7",
			"paths" : 
			[
				"external/mimalloc/include/mimalloc-override.h"
			],
			"type" : "file"
		},
		{
			"backtrace" : 6,
			"component" : "Unspecified",
			"destination" : "include/mimalloc-1.7",
			"paths" : 
			[
				"external/mimalloc/include/mimalloc-new-delete.h"
			],
			"type" : "file"
		},
		{
			"backtrace" : 7,
			"component" : "Unspecified",
			"destination" : "share/mimalloc-1.7/cmake",
			"paths" : 
			[
				"external/mimalloc/cmake/mimalloc-config.cmake"
			],
			"type" : "file"
		},
		{
			"backtrace" : 8,
			"component" : "Unspecified",
			"destination" : "share/mimalloc-1.7/cmake",
			"paths" : 
			[
				"external/mimalloc/cmake/mimalloc-config-version.cmake"
			],
			"type" : "file"
		},
		{
			"backtrace" : 9,
			"component" : "Unspecified",
			"destination" : "lib/mimalloc-1.7",
			"paths" : 
			[
				{
					"from" : "build/external/mimalloc/CMakeFiles/mimalloc-obj.dir/src/static.c.obj",
					"to" : "mimalloc-debug.obj"
				}
			],
			"type" : "file"
		}
	],
	"paths" : 
	{
		"build" : "external/mimalloc",
		"source" : "external/mimalloc"
	}
}
