{
	"backtraceGraph" : 
	{
		"commands" : 
		[
			"install"
		],
		"files" : 
		[
			"external/glfwpp/external/glfw/CMakeLists.txt"
		],
		"nodes" : 
		[
			{
				"file" : 0
			},
			{
				"command" : 0,
				"file" : 0,
				"line" : 294,
				"parent" : 0
			},
			{
				"command" : 0,
				"file" : 0,
				"line" : 297,
				"parent" : 0
			},
			{
				"command" : 0,
				"file" : 0,
				"line" : 301,
				"parent" : 0
			},
			{
				"command" : 0,
				"file" : 0,
				"line" : 304,
				"parent" : 0
			}
		]
	},
	"installers" : 
	[
		{
			"backtrace" : 1,
			"component" : "Unspecified",
			"destination" : "include",
			"paths" : 
			[
				"external/glfwpp/external/glfw/include/GLFW"
			],
			"type" : "directory"
		},
		{
			"backtrace" : 2,
			"component" : "Unspecified",
			"destination" : "lib/cmake/glfw3",
			"paths" : 
			[
				"build/external/glfwpp/external/glfw/src/glfw3Config.cmake",
				"build/external/glfwpp/external/glfw/src/glfw3ConfigVersion.cmake"
			],
			"type" : "file"
		},
		{
			"backtrace" : 3,
			"component" : "Unspecified",
			"destination" : "lib/cmake/glfw3",
			"exportName" : "glfwTargets",
			"exportTargets" : 
			[
				{
					"id" : "glfw::@987cbf6fc3f4e84e4fb7",
					"index" : 1
				}
			],
			"paths" : 
			[
				"external/glfwpp/external/glfw/CMakeFiles/Export/lib/cmake/glfw3/glfw3Targets.cmake"
			],
			"type" : "export"
		},
		{
			"backtrace" : 4,
			"component" : "Unspecified",
			"destination" : "lib/pkgconfig",
			"paths" : 
			[
				"build/external/glfwpp/external/glfw/src/glfw3.pc"
			],
			"type" : "file"
		}
	],
	"paths" : 
	{
		"build" : "external/glfwpp/external/glfw",
		"source" : "external/glfwpp/external/glfw"
	}
}
